{
  "id": "1.1",
  "name": "Basic Greetings",
  "pages": [
    {
      "type": "explanation",
      "id": "1.1.1",
      "content": [
        { "type": "title", "value": "Saying Hello" },
        {
          "type": "text",
          "value": "In Cantonese, we use <strong>你好</strong> to greet people."
        },
        {
          "type": "example",
          "cantonese": "你好。",
          "romanization": "nei5 hou2.",
          "translation": "Hello."
        }
      ]
    },
    { "type": "reading", "id": "1.1.2" },
    { "type": "unscramble", "id": "1.1.3" }
  ]
}
